<?xml version="1.0" encoding="utf-8"?>
<!DOCTYPE hibernate-mapping PUBLIC "-//Hibernate/Hibernate Mapping DTD 3.0//EN"
"http://hibernate.sourceforge.net/hibernate-mapping-3.0.dtd">
<!-- 
    Mapping file autogenerated by MyEclipse Persistence Tools
-->
<hibernate-mapping>
    <class name="com.wyz.hibernate.pojo.TTemiClient" table="T_TEMI_CLIENT" catalog="drp">
        <id name="id" type="long">
            <column name="ID" precision="10" scale="0" />
            <generator class="assigned" />
        </id>
        <property name="pid" type="long">
            <column name="PID" precision="10" scale="0" />
        </property>
        <property name="temiClientLevelId" type="string">
            <column name="TEMI_CLIENT_LEVEL_ID" length="3" />
        </property>
        <property name="name" type="string">
            <column name="NAME" length="40" not-null="true" />
        </property>
        <property name="temiClientId" type="string">
            <column name="TEMI_CLIENT_ID" length="10" />
        </property>
        <property name="contactTel" type="string">
            <column name="CONTACT_TEL" length="30" />
        </property>
        <property name="contactor" type="string">
            <column name="CONTACTOR" length="20" />
        </property>
        <property name="address" type="string">
            <column name="ADDRESS" length="30" />
        </property>
        <property name="zipCode" type="string">
            <column name="ZIP_CODE" length="10" />
        </property>
        <property name="isLeaf" type="string">
            <column name="IS_LEAF" length="1" not-null="true">
                <comment>Y:Ҷ</comment>
            </column>
        </property>
        <property name="isTemiClient" type="string">
            <column name="IS_TEMI_CLIENT" length="1" not-null="true">
                <comment>Y:</comment>
            </column>
        </property>
    </class>
</hibernate-mapping>
